pulumiverse_cpln/__init__.py
pulumiverse_cpln/_inputs.py
pulumiverse_cpln/_utilities.py
pulumiverse_cpln/agent.py
pulumiverse_cpln/audit_context.py
pulumiverse_cpln/catalog_template.py
pulumiverse_cpln/cloud_account.py
pulumiverse_cpln/custom_location.py
pulumiverse_cpln/domain.py
pulumiverse_cpln/domain_route.py
pulumiverse_cpln/get_cloud_account.py
pulumiverse_cpln/get_gvc.py
pulumiverse_cpln/get_image.py
pulumiverse_cpln/get_images.py
pulumiverse_cpln/get_location.py
pulumiverse_cpln/get_locations.py
pulumiverse_cpln/get_org.py
pulumiverse_cpln/get_secret.py
pulumiverse_cpln/get_workload.py
pulumiverse_cpln/group.py
pulumiverse_cpln/gvc.py
pulumiverse_cpln/identity.py
pulumiverse_cpln/ip_set.py
pulumiverse_cpln/location.py
pulumiverse_cpln/mk8s.py
pulumiverse_cpln/mk8s_kubeconfig.py
pulumiverse_cpln/org.py
pulumiverse_cpln/org_logging.py
pulumiverse_cpln/org_tracing.py
pulumiverse_cpln/outputs.py
pulumiverse_cpln/policy.py
pulumiverse_cpln/provider.py
pulumiverse_cpln/pulumi-plugin.json
pulumiverse_cpln/py.typed
pulumiverse_cpln/secret.py
pulumiverse_cpln/service_account.py
pulumiverse_cpln/service_account_key.py
pulumiverse_cpln/volume_set.py
pulumiverse_cpln/workload.py
pulumiverse_cpln/config/__init__.py
pulumiverse_cpln/config/__init__.pyi
pulumiverse_cpln/config/vars.py
pulumiverse_cpln-0.0.77.dist-info/METADATA
pulumiverse_cpln-0.0.77.dist-info/WHEEL
pulumiverse_cpln-0.0.77.dist-info/top_level.txt
pulumiverse_cpln-0.0.77.dist-info/RECORD
